tweet_nlp_toolkit/__init__.py
tweet_nlp_toolkit/__version__.py
tweet_nlp_toolkit/constants.py
tweet_nlp_toolkit/utils.py
tweet_nlp_toolkit/prep/__init__.py
tweet_nlp_toolkit/prep/regexes.py
tweet_nlp_toolkit/prep/text_parser.py
tweet_nlp_toolkit/prep/text_prep.py
tweet_nlp_toolkit/prep/token.py
tweet_nlp_toolkit/prep/tokenizer.py
tweet_nlp_toolkit/prep/word_segmentation.py
tweet_nlp_toolkit-1.0.5.dist-info/LICENSE
tweet_nlp_toolkit-1.0.5.dist-info/METADATA
tweet_nlp_toolkit-1.0.5.dist-info/WHEEL
tweet_nlp_toolkit-1.0.5.dist-info/top_level.txt
tweet_nlp_toolkit-1.0.5.dist-info/RECORD
