Metadata-Version: 2.1
Name: tweet-nlp-toolkit
Version: 1.0.5
Summary: NLP toolkit for tweets
Home-page: https://github.com/hitchhicker/tweet_nlp_toolkit
Author: Bokai Yu
License: UNKNOWN
Platform: UNKNOWN
Classifier: License :: OSI Approved :: Apache Software License
Classifier: Programming Language :: Python :: 3.6
Requires-Dist: pycld2 (==0.41)
Requires-Dist: mecab-python3 (==0.996.5)
Requires-Dist: contractions (==0.0.25)
Requires-Dist: emoji (==1.6.3)
Requires-Dist: mosestokenizer (==1.2.1)
Requires-Dist: jieba (==0.42.1)
Requires-Dist: pythainlp (==2.3.2)
